{
    "camera_angle_x": 0.3395565450191498,
    "frames": [
        {
            "file_path": "train/0001",
            "transform_matrix": [
                [
                    1.0,
                    0.0,
                    0.0,
                    0.0
                ],
                [
                    0.0,
                    -4.371138828673793e-08,
                    -1.0,
                    -4.0
                ],
                [
                    0.0,
                    1.0,
                    -4.371138828673793e-08,
                    0.0
                ],
                [
                    0.0,
                    0.0,
                    0.0,
                    1.0
                ]
            ]
        },
        {
            "file_path": "train/0002",
            "transform_matrix": [
                [
                    0.9979866743087769,
                    2.772347684754095e-09,
                    0.06342392414808273,
                    0.25369569659233093
                ],
                [
                    0.06342392414808273,
                    -4.362338401620036e-08,
                    -0.9979866743087769,
                    -3.9919466972351074
                ],
                [
                    0.0,
                    1.0,
                    -4.371138828673793e-08,
                    0.0
                ],
                [
                    0.0,
                    0.0,
                    0.0,
                    1.0
                ]
            ]
        },
        {
            "file_path": "train/0003",
            "transform_matrix": [
                [
                    0.9919548034667969,
                    5.533531854950979e-09,
                    0.1265924572944641,
                    0.5063698291778564
                ],
                [
                    0.1265924572944641,
                    -4.335972292324186e-08,
                    -0.9919548034667969,
                    -3.9678192138671875
                ],
                [
                    0.0,
                    1.0,
                    -4.371138828673793e-08,
                    0.0
                ],
                [
                    0.0,
                    0.0,
                    0.0,
                    1.0
                ]
            ]
        },
        {
            "file_path": "train/0004",
            "transform_matrix": [
                [
                    0.9819287061691284,
                    8.272434293132847e-09,
                    0.18925124406814575,
                    0.757004976272583
                ],
                [
                    0.18925124406814575,
                    -4.292146726925239e-08,
                    -0.9819287061691284,
                    -3.9277148246765137
                ],
                [
                    0.0,
                    1.0,
                    -4.371138828673793e-08,
                    0.0
                ],
                [
                    0.0,
                    0.0,
                    0.0,
                    1.0
                ]
            ]
        },
        {
            "file_path": "train/0005",
            "transform_matrix": [
                [
                    0.9679486751556396,
                    1.09780273760407e-08,
                    0.251147985458374,
                    1.004591941833496
                ],
                [
                    0.251147985458374,
                    -4.231037920021663e-08,
                    -0.9679486751556396,
                    -3.8717947006225586
                ],
                [
                    0.0,
                    1.0,
                    -4.371138828673793e-08,
                    0.0
                ],
                [
                    0.0,
                    0.0,
                    0.0,
                    1.0
                ]
            ]
        },
        {
            "file_path": "train/0006",
            "transform_matrix": [
                [
                    0.9500710964202881,
                    1.3639414930821658e-08,
                    0.31203344464302063,
                    1.2481337785720825
                ],
                [
                    0.31203344464302063,
                    -4.152892785214135e-08,
                    -0.9500710964202881,
                    -3.8002843856811523
                ],
                [
                    0.0,
                    1.0,
                    -4.371138828673793e-08,
                    0.0
                ],
                [
                    0.0,
                    0.0,
                    0.0,
                    1.0
                ]
            ]
        },
        {
            "file_path": "train/0007",
            "transform_matrix": [
                [
                    0.9283679127693176,
                    1.624588286119888e-08,
                    0.3716624677181244,
                    1.4866498708724976
                ],
                [
                    0.3716624677181244,
                    -4.058025027120493e-08,
                    -0.9283679127693176,
                    -3.7134716510772705
                ],
                [
                    0.0,
                    1.0,
                    -4.371138828673793e-08,
                    0.0
                ],
                [
                    0.0,
                    0.0,
                    0.0,
                    1.0
                ]
            ]
        },
        {
            "file_path": "train/0008",
            "transform_matrix": [
                [
                    0.902926504611969,
                    1.8786932898251507e-08,
                    0.42979493737220764,
                    1.7191797494888306
                ],
                [
                    0.42979493737220764,
                    -3.946817273003944e-08,
                    -0.902926504611969,
                    -3.611706018447876
                ],
                [
                    0.0,
                    1.0,
                    -4.371138828673793e-08,
                    0.0
                ],
                [
                    0.0,
                    0.0,
                    0.0,
                    1.0
                ]
            ]
        },
        {
            "file_path": "train/0009",
            "transform_matrix": [
                [
                    0.8738493919372559,
                    2.1252335002941436e-08,
                    0.48619675636291504,
                    1.9447870254516602
                ],
                [
                    0.48619675636291504,
                    -3.819717164788017e-08,
                    -0.8738493919372559,
                    -3.4953975677490234
                ],
                [
                    0.0,
                    1.0,
                    -4.371138828673793e-08,
                    0.0
                ],
                [
                    0.0,
                    0.0,
                    0.0,
                    1.0
                ]
            ]
        },
        {
            "file_path": "train/0010",
            "transform_matrix": [
                [
                    0.8412535190582275,
                    2.3632159340536418e-08,
                    0.5406407713890076,
                    2.1625630855560303
                ],
                [
                    0.5406407713890076,
                    -3.6772359379710906e-08,
                    -0.8412535190582275,
                    -3.36501407623291
                ],
                [
                    0.0,
                    1.0,
                    -4.371138828673793e-08,
                    0.0
                ],
                [
                    0.0,
                    0.0,
                    0.0,
                    1.0
                ]
            ]
        },
        {
            "file_path": "train/0011",
            "transform_matrix": [
                [
                    0.805270254611969,
                    2.5916829571315247e-08,
                    0.5929079651832581,
                    2.3716318607330322
                ],
                [
                    0.5929079651832581,
                    -3.5199480663550275e-08,
                    -0.805270254611969,
                    -3.221081018447876
                ],
                [
                    0.0,
                    1.0,
                    -4.371138828673793e-08,
                    0.0
                ],
                [
                    0.0,
                    0.0,
                    0.0,
                    1.0
                ]
            ]
        },
        {
            "file_path": "train/0012",
            "transform_matrix": [
                [
                    0.7660444378852844,
                    2.809714061413615e-08,
                    0.6427876353263855,
                    2.571150541305542
                ],
                [
                    0.6427876353263855,
                    -3.34848664351739e-08,
                    -0.7660444378852844,
                    -3.0641777515411377
                ],
                [
                    0.0,
                    1.0,
                    -4.371138828673793e-08,
                    0.0
                ],
                [
                    0.0,
                    0.0,
                    0.0,
                    1.0
                ]
            ]
        },
        {
            "file_path": "train/0013",
            "transform_matrix": [
                [
                    0.7237340211868286,
                    3.0164311937141974e-08,
                    0.6900790333747864,
                    2.7603161334991455
                ],
                [
                    0.6900790333747864,
                    -3.1635419617259686e-08,
                    -0.7237340211868286,
                    -2.8949360847473145
                ],
                [
                    0.0,
                    1.0,
                    -4.371138828673793e-08,
                    0.0
                ],
                [
                    0.0,
                    0.0,
                    0.0,
                    1.0
                ]
            ]
        },
        {
            "file_path": "train/0014",
            "transform_matrix": [
                [
                    0.6785093545913696,
                    3.2110023084896966e-08,
                    0.7345917224884033,
                    2.9383668899536133
                ],
                [
                    0.7345917224884033,
                    -2.9658586697678402e-08,
                    -0.6785093545913696,
                    -2.7140374183654785
                ],
                [
                    0.0,
                    1.0,
                    -4.371138828673793e-08,
                    0.0
                ],
                [
                    0.0,
                    0.0,
                    0.0,
                    1.0
                ]
            ]
        },
        {
            "file_path": "train/0015",
            "transform_matrix": [
                [
                    0.6305525898933411,
                    3.392644387645305e-08,
                    0.7761465311050415,
                    3.104586124420166
                ],
                [
                    0.7761465311050415,
                    -2.756232930778424e-08,
                    -0.6305525898933411,
                    -2.5222103595733643
                ],
                [
                    0.0,
                    1.0,
                    -4.371138828673793e-08,
                    0.0
                ],
                [
                    0.0,
                    0.0,
                    0.0,
                    1.0
                ]
            ]
        },
        {
            "file_path": "train/0016",
            "transform_matrix": [
                [
                    0.58005690574646,
                    3.560624506349086e-08,
                    0.8145759701728821,
                    3.2583038806915283
                ],
                [
                    0.8145759701728821,
                    -2.5355092247991706e-08,
                    -0.58005690574646,
                    -2.32022762298584
                ],
                [
                    0.0,
                    1.0,
                    -4.371138828673793e-08,
                    0.0
                ],
                [
                    0.0,
                    0.0,
                    0.0,
                    1.0
                ]
            ]
        },
        {
            "file_path": "train/0017",
            "transform_matrix": [
                [
                    0.5272254347801208,
                    3.7142676490020676e-08,
                    0.8497254252433777,
                    3.3989017009735107
                ],
                [
                    0.8497254252433777,
                    -2.3045755526140965e-08,
                    -0.5272254347801208,
                    -2.1089017391204834
                ],
                [
                    0.0,
                    1.0,
                    -4.371138828673793e-08,
                    0.0
                ],
                [
                    0.0,
                    0.0,
                    0.0,
                    1.0
                ]
            ]
        },
        {
            "file_path": "train/0018",
            "transform_matrix": [
                [
                    0.47227102518081665,
                    3.8529552881527707e-08,
                    0.8814533948898315,
                    3.525813579559326
                ],
                [
                    0.8814533948898315,
                    -2.0643621922999955e-08,
                    -0.47227102518081665,
                    -1.8890841007232666
                ],
                [
                    0.0,
                    1.0,
                    -4.371138828673793e-08,
                    0.0
                ],
                [
                    0.0,
                    0.0,
                    0.0,
                    1.0
                ]
            ]
        },
        {
            "file_path": "train/0019",
            "transform_matrix": [
                [
                    0.41541504859924316,
                    3.976127516125416e-08,
                    0.9096319675445557,
                    3.6385278701782227
                ],
                [
                    0.9096319675445557,
                    -1.815836903062973e-08,
                    -0.41541504859924316,
                    -1.6616601943969727
                ],
                [
                    0.0,
                    1.0,
                    -4.371138828673793e-08,
                    0.0
                ],
                [
                    0.0,
                    0.0,
                    0.0,
                    1.0
                ]
            ]
        },
        {
            "file_path": "train/0020",
            "transform_matrix": [
                [
                    0.35688623785972595,
                    4.083289795175915e-08,
                    0.934147834777832,
                    3.736591339111328
                ],
                [
                    0.934147834777832,
                    -1.559999240896559e-08,
                    -0.35688623785972595,
                    -1.4275449514389038
                ],
                [
                    0.0,
                    1.0,
                    -4.371138828673793e-08,
                    0.0
                ],
                [
                    0.0,
                    0.0,
                    0.0,
                    1.0
                ]
            ]
        },
        {
            "file_path": "train/0021",
            "transform_matrix": [
                [
                    0.2969203591346741,
                    4.174010115320925e-08,
                    0.9549022316932678,
                    3.8196089267730713
                ],
                [
                    0.9549022316932678,
                    -1.2978801144925e-08,
                    -0.2969203591346741,
                    -1.1876814365386963
                ],
                [
                    0.0,
                    1.0,
                    -4.371138828673793e-08,
                    0.0
                ],
                [
                    0.0,
                    0.0,
                    0.0,
                    1.0
                ]
            ]
        },
        {
            "file_path": "train/0022",
            "transform_matrix": [
                [
                    0.23575888574123383,
                    4.247923257594266e-08,
                    0.9718115925788879,
                    3.8872463703155518
                ],
                [
                    0.9718115925788879,
                    -1.0305348574490836e-08,
                    -0.23575888574123383,
                    -0.9430355429649353
                ],
                [
                    0.0,
                    1.0,
                    -4.371138828673793e-08,
                    0.0
                ],
                [
                    0.0,
                    0.0,
                    0.0,
                    1.0
                ]
            ]
        },
        {
            "file_path": "train/0023",
            "transform_matrix": [
                [
                    0.17364810407161713,
                    4.304731504589654e-08,
                    0.9848077893257141,
                    3.9392311573028564
                ],
                [
                    0.9848077893257141,
                    -7.590399420109861e-09,
                    -0.17364810407161713,
                    -0.6945924162864685
                ],
                [
                    0.0,
                    1.0,
                    -4.371138828673793e-08,
                    0.0
                ],
                [
                    0.0,
                    0.0,
                    0.0,
                    1.0
                ]
            ]
        },
        {
            "file_path": "train/0024",
            "transform_matrix": [
                [
                    0.11083821207284927,
                    4.344206061546174e-08,
                    0.9938384890556335,
                    3.975353956222534
                ],
                [
                    0.9938384890556335,
                    -4.844892043109894e-09,
                    -0.11083821207284927,
                    -0.4433528482913971
                ],
                [
                    0.0,
                    1.0,
                    -4.371138828673793e-08,
                    0.0
                ],
                [
                    0.0,
                    0.0,
                    0.0,
                    1.0
                ]
            ]
        },
        {
            "file_path": "train/0025",
            "transform_matrix": [
                [
                    0.04758189618587494,
                    4.3661877668910165e-08,
                    0.9988673329353333,
                    3.995469331741333
                ],
                [
                    0.9988673329353333,
                    -2.0798707200953004e-09,
                    -0.04758189618587494,
                    -0.19032758474349976
                ],
                [
                    0.0,
                    1.0,
                    -4.371138828673793e-08,
                    0.0
                ],
                [
                    0.0,
                    0.0,
                    0.0,
                    1.0
                ]
            ]
        },
        {
            "file_path": "train/0026",
            "transform_matrix": [
                [
                    -0.01586601510643959,
                    4.370588513324947e-08,
                    0.9998741149902344,
                    3.9994964599609375
                ],
                [
                    0.9998741149902344,
                    6.935255703055532e-10,
                    0.01586601510643959,
                    0.06346406042575836
                ],
                [
                    0.0,
                    1.0,
                    -4.371138828673793e-08,
                    0.0
                ],
                [
                    0.0,
                    0.0,
                    0.0,
                    1.0
                ]
            ]
        },
        {
            "file_path": "train/0027",
            "transform_matrix": [
                [
                    -0.0792500376701355,
                    4.357390537279571e-08,
                    0.9968547821044922,
                    3.9874191284179688
                ],
                [
                    0.9968547821044922,
                    3.4641292057102646e-09,
                    0.0792500376701355,
                    0.317000150680542
                ],
                [
                    0.0,
                    1.0,
                    -4.371138828673793e-08,
                    0.0
                ],
                [
                    0.0,
                    0.0,
                    0.0,
                    1.0
                ]
            ]
        },
        {
            "file_path": "train/0028",
            "transform_matrix": [
                [
                    -0.14231495559215546,
                    4.326646774188703e-08,
                    0.9898214340209961,
                    3.9592857360839844
                ],
                [
                    0.9898214340209961,
                    6.220784332100493e-09,
                    0.14231495559215546,
                    0.5692598223686218
                ],
                [
                    0.0,
                    1.0,
                    -4.371138828673793e-08,
                    0.0
                ],
                [
                    0.0,
                    0.0,
                    0.0,
                    1.0
                ]
            ]
        },
        {
            "file_path": "train/0029",
            "transform_matrix": [
                [
                    -0.20480680465698242,
                    4.278481213759733e-08,
                    0.9788024425506592,
                    3.9152097702026367
                ],
                [
                    0.9788024425506592,
                    8.952389940475314e-09,
                    0.20480680465698242,
                    0.8192272186279297
                ],
                [
                    0.0,
                    1.0,
                    -4.371138828673793e-08,
                    0.0
                ],
                [
                    0.0,
                    0.0,
                    0.0,
                    1.0
                ]
            ]
        },
        {
            "file_path": "train/0030",
            "transform_matrix": [
                [
                    -0.2664737403392792,
                    4.2130878341595235e-08,
                    0.9638421535491943,
                    3.8553686141967773
                ],
                [
                    0.9638421535491943,
                    1.1647936837277939e-08,
                    0.2664737403392792,
                    1.0658949613571167
                ],
                [
                    0.0,
                    1.0,
                    -4.371138828673793e-08,
                    0.0
                ],
                [
                    0.0,
                    0.0,
                    0.0,
                    1.0
                ]
            ]
        },
        {
            "file_path": "train/0031",
            "transform_matrix": [
                [
                    -0.32706794142723083,
                    4.130729891471674e-08,
                    0.9450008273124695,
                    3.780003309249878
                ],
                [
                    0.9450008273124695,
                    1.4296594130769336e-08,
                    0.32706794142723083,
                    1.3082717657089233
                ],
                [
                    0.0,
                    1.0,
                    -4.371138828673793e-08,
                    0.0
                ],
                [
                    0.0,
                    0.0,
                    0.0,
                    1.0
                ]
            ]
        },
        {
            "file_path": "train/0032",
            "transform_matrix": [
                [
                    -0.38634511828422546,
                    4.031738498611048e-08,
                    0.9223542809486389,
                    3.6894171237945557
                ],
                [
                    0.9223542809486389,
                    1.688768236363103e-08,
                    0.38634511828422546,
                    1.5453804731369019
                ],
                [
                    0.0,
                    1.0,
                    -4.371138828673793e-08,
                    0.0
                ],
                [
                    0.0,
                    0.0,
                    0.0,
                    1.0
                ]
            ]
        },
        {
            "file_path": "train/0033",
            "transform_matrix": [
                [
                    -0.4440666437149048,
                    3.916512980595144e-08,
                    0.8959937691688538,
                    3.583975076675415
                ],
                [
                    0.8959937691688538,
                    1.9410769880323642e-08,
                    0.4440666437149048,
                    1.7762665748596191
                ],
                [
                    0.0,
                    1.0,
                    -4.371138828673793e-08,
                    0.0
                ],
                [
                    0.0,
                    0.0,
                    0.0,
                    1.0
                ]
            ]
        },
        {
            "file_path": "train/0034",
            "transform_matrix": [
                [
                    -0.5000000596046448,
                    3.785517321830412e-08,
                    0.8660253882408142,
                    3.464101552963257
                ],
                [
                    0.8660253882408142,
                    2.1855695919725804e-08,
                    0.5000000596046448,
                    2.000000238418579
                ],
                [
                    0.0,
                    1.0,
                    -4.371138828673793e-08,
                    0.0
                ],
                [
                    0.0,
                    0.0,
                    0.0,
                    1.0
                ]
            ]
        },
        {
            "file_path": "train/0035",
            "transform_matrix": [
                [
                    -0.5539201498031616,
                    3.63927803448405e-08,
                    0.8325697779655457,
                    3.3302791118621826
                ],
                [
                    0.8325697779655457,
                    2.4212619464947238e-08,
                    0.5539201498031616,
                    2.2156805992126465
                ],
                [
                    0.0,
                    1.0,
                    -4.371138828673793e-08,
                    0.0
                ],
                [
                    0.0,
                    0.0,
                    0.0,
                    1.0
                ]
            ]
        },
        {
            "file_path": "train/0036",
            "transform_matrix": [
                [
                    -0.6056097745895386,
                    3.4783852242981084e-08,
                    0.79576176404953,
                    3.18304705619812
                ],
                [
                    0.79576176404953,
                    2.647204411232451e-08,
                    0.6056097745895386,
                    2.4224390983581543
                ],
                [
                    0.0,
                    1.0,
                    -4.371138828673793e-08,
                    0.0
                ],
                [
                    0.0,
                    0.0,
                    0.0,
                    1.0
                ]
            ]
        },
        {
            "file_path": "train/0037",
            "transform_matrix": [
                [
                    -0.6548606753349304,
                    3.303486550976231e-08,
                    0.7557496428489685,
                    3.022998571395874
                ],
                [
                    0.7557496428489685,
                    2.8624869585769375e-08,
                    0.6548606753349304,
                    2.6194427013397217
                ],
                [
                    0.0,
                    1.0,
                    -4.371138828673793e-08,
                    0.0
                ],
                [
                    0.0,
                    0.0,
                    0.0,
                    1.0
                ]
            ]
        },
        {
            "file_path": "train/0038",
            "transform_matrix": [
                [
                    -0.7014748454093933,
                    3.1152854518268214e-08,
                    0.7126942276954651,
                    2.8507769107818604
                ],
                [
                    0.7126942276954651,
                    3.066243792204659e-08,
                    0.7014748454093933,
                    2.8058993816375732
                ],
                [
                    0.0,
                    1.0,
                    -4.371138828673793e-08,
                    0.0
                ],
                [
                    0.0,
                    0.0,
                    0.0,
                    1.0
                ]
            ]
        },
        {
            "file_path": "train/0039",
            "transform_matrix": [
                [
                    -0.7452644109725952,
                    2.914539898313251e-08,
                    0.6667690277099609,
                    2.6670761108398438
                ],
                [
                    0.6667690277099609,
                    3.2576540576201296e-08,
                    0.7452644109725952,
                    2.981057643890381
                ],
                [
                    0.0,
                    1.0,
                    -4.371138828673793e-08,
                    0.0
                ],
                [
                    0.0,
                    0.0,
                    0.0,
                    1.0
                ]
            ]
        },
        {
            "file_path": "train/0040",
            "transform_matrix": [
                [
                    -0.7860531210899353,
                    2.7020588433401826e-08,
                    0.6181589961051941,
                    2.4726359844207764
                ],
                [
                    0.6181589961051941,
                    3.4359473488621006e-08,
                    0.7860531210899353,
                    3.144212484359741
                ],
                [
                    0.0,
                    1.0,
                    -4.371138828673793e-08,
                    0.0
                ],
                [
                    0.0,
                    0.0,
                    0.0,
                    1.0
                ]
            ]
        },
        {
            "file_path": "train/0041",
            "transform_matrix": [
                [
                    -0.823676586151123,
                    2.47869724745442e-08,
                    0.5670598149299622,
                    2.2682392597198486
                ],
                [
                    0.5670598149299622,
                    3.600404596681983e-08,
                    0.823676586151123,
                    3.294706344604492
                ],
                [
                    0.0,
                    1.0,
                    -4.371138828673793e-08,
                    0.0
                ],
                [
                    0.0,
                    0.0,
                    0.0,
                    1.0
                ]
            ]
        },
        {
            "file_path": "train/0042",
            "transform_matrix": [
                [
                    -0.8579834699630737,
                    2.245355013030803e-08,
                    0.5136773586273193,
                    2.0547094345092773
                ],
                [
                    0.5136773586273193,
                    3.75036499633552e-08,
                    0.8579834699630737,
                    3.431933879852295
                ],
                [
                    0.0,
                    1.0,
                    -4.371138828673793e-08,
                    0.0
                ],
                [
                    0.0,
                    0.0,
                    0.0,
                    1.0
                ]
            ]
        },
        {
            "file_path": "train/0043",
            "transform_matrix": [
                [
                    -0.8888354897499084,
                    2.0029714775660068e-08,
                    0.45822644233703613,
                    1.8329057693481445
                ],
                [
                    0.45822644233703613,
                    3.885223165411844e-08,
                    0.8888354897499084,
                    3.555341958999634
                ],
                [
                    0.0,
                    1.0,
                    -4.371138828673793e-08,
                    0.0
                ],
                [
                    0.0,
                    0.0,
                    0.0,
                    1.0
                ]
            ]
        },
        {
            "file_path": "train/0044",
            "transform_matrix": [
                [
                    -0.9161084890365601,
                    1.7525223938719137e-08,
                    0.40093040466308594,
                    1.6037216186523438
                ],
                [
                    0.40093040466308594,
                    4.004437315074938e-08,
                    0.9161084890365601,
                    3.6644339561462402
                ],
                [
                    0.0,
                    1.0,
                    -4.371138828673793e-08,
                    0.0
                ],
                [
                    0.0,
                    0.0,
                    0.0,
                    1.0
                ]
            ]
        },
        {
            "file_path": "train/0045",
            "transform_matrix": [
                [
                    -0.9396926760673523,
                    1.495016910268987e-08,
                    0.3420200049877167,
                    1.3680800199508667
                ],
                [
                    0.3420200049877167,
                    4.107527118435428e-08,
                    0.9396926760673523,
                    3.758770704269409
                ],
                [
                    0.0,
                    1.0,
                    -4.371138828673793e-08,
                    0.0
                ],
                [
                    0.0,
                    0.0,
                    0.0,
                    1.0
                ]
            ]
        },
        {
            "file_path": "train/0046",
            "transform_matrix": [
                [
                    -0.9594930410385132,
                    1.2314913533373328e-08,
                    0.28173238039016724,
                    1.126929521560669
                ],
                [
                    0.28173238039016724,
                    4.194077263264262e-08,
                    0.9594930410385132,
                    3.8379721641540527
                ],
                [
                    0.0,
                    1.0,
                    -4.371138828673793e-08,
                    0.0
                ],
                [
                    0.0,
                    0.0,
                    0.0,
                    1.0
                ]
            ]
        },
        {
            "file_path": "train/0047",
            "transform_matrix": [
                [
                    -0.9754297733306885,
                    9.630079844669126e-09,
                    0.22031055390834808,
                    0.8812422156333923
                ],
                [
                    0.22031055390834808,
                    4.263738873078182e-08,
                    0.9754297733306885,
                    3.901719093322754
                ],
                [
                    0.0,
                    1.0,
                    -4.371138828673793e-08,
                    0.0
                ],
                [
                    0.0,
                    0.0,
                    0.0,
                    1.0
                ]
            ]
        },
        {
            "file_path": "train/0048",
            "transform_matrix": [
                [
                    -0.9874389171600342,
                    6.9064496344140025e-09,
                    0.1580011546611786,
                    0.6320046186447144
                ],
                [
                    0.1580011546611786,
                    4.316232704582035e-08,
                    0.9874389171600342,
                    3.9497556686401367
                ],
                [
                    0.0,
                    1.0,
                    -4.371138828673793e-08,
                    0.0
                ],
                [
                    0.0,
                    0.0,
                    0.0,
                    1.0
                ]
            ]
        },
        {
            "file_path": "train/0049",
            "transform_matrix": [
                [
                    -0.9954719543457031,
                    4.1550300977633015e-09,
                    0.09505600482225418,
                    0.3802240192890167
                ],
                [
                    0.09505600482225418,
                    4.3513459502264595e-08,
                    0.9954719543457031,
                    3.9818878173828125
                ],
                [
                    0.0,
                    1.0,
                    -4.371138828673793e-08,
                    0.0
                ],
                [
                    0.0,
                    0.0,
                    0.0,
                    1.0
                ]
            ]
        },
        {
            "file_path": "train/0050",
            "transform_matrix": [
                [
                    -0.9994965195655823,
                    1.386868841990463e-09,
                    0.0317278616130352,
                    0.1269114464521408
                ],
                [
                    0.0317278616130352,
                    4.368937922549776e-08,
                    0.9994965195655823,
                    3.997986078262329
                ],
                [
                    0.0,
                    1.0,
                    -4.371138828673793e-08,
                    0.0
                ],
                [
                    0.0,
                    0.0,
                    0.0,
                    1.0
                ]
            ]
        },
        {
            "file_path": "train/0051",
            "transform_matrix": [
                [
                    -0.9994965195655823,
                    -1.3868765025293328e-09,
                    -0.03172803670167923,
                    -0.12691214680671692
                ],
                [
                    -0.03172803670167923,
                    4.368937922549776e-08,
                    0.9994965195655823,
                    3.997986078262329
                ],
                [
                    0.0,
                    1.0,
                    -4.371138828673793e-08,
                    0.0
                ],
                [
                    0.0,
                    0.0,
                    0.0,
                    1.0
                ]
            ]
        },
        {
            "file_path": "train/0052",
            "transform_matrix": [
                [
                    -0.9954718947410583,
                    -4.155037647279869e-09,
                    -0.09505617618560791,
                    -0.38022470474243164
                ],
                [
                    -0.09505617618560791,
                    4.3513459502264595e-08,
                    0.9954718947410583,
                    3.9818875789642334
                ],
                [
                    0.0,
                    1.0,
                    -4.371138828673793e-08,
                    0.0
                ],
                [
                    0.0,
                    0.0,
                    0.0,
                    1.0
                ]
            ]
        },
        {
            "file_path": "train/0053",
            "transform_matrix": [
                [
                    -0.9874388575553894,
                    -6.9064673979823965e-09,
                    -0.15800155699253082,
                    -0.6320062279701233
                ],
                [
                    -0.15800155699253082,
                    4.316232349310667e-08,
                    0.9874388575553894,
                    3.9497554302215576
                ],
                [
                    0.0,
                    1.0,
                    -4.371138828673793e-08,
                    0.0
                ],
                [
                    0.0,
                    0.0,
                    0.0,
                    1.0
                ]
            ]
        },
        {
            "file_path": "train/0054",
            "transform_matrix": [
                [
                    -0.9754297733306885,
                    -9.630077180133867e-09,
                    -0.2203104943037033,
                    -0.8812419772148132
                ],
                [
                    -0.2203104943037033,
                    4.263738873078182e-08,
                    0.9754297733306885,
                    3.901719093322754
                ],
                [
                    0.0,
                    1.0,
                    -4.371138828673793e-08,
                    0.0
                ],
                [
                    0.0,
                    0.0,
                    0.0,
                    1.0
                ]
            ]
        },
        {
            "file_path": "train/0055",
            "transform_matrix": [
                [
                    -0.9594929218292236,
                    -1.2314930408763303e-08,
                    -0.2817327678203583,
                    -1.126931071281433
                ],
                [
                    -0.2817327678203583,
                    4.194076907992894e-08,
                    0.9594929218292236,
                    3.8379716873168945
                ],
                [
                    0.0,
                    1.0,
                    -4.371138828673793e-08,
                    0.0
                ],
                [
                    0.0,
                    0.0,
                    0.0,
                    1.0
                ]
            ]
        },
        {
            "file_path": "train/0056",
            "transform_matrix": [
                [
                    -0.9396926164627075,
                    -1.4950176208117227e-08,
                    -0.3420201539993286,
                    -1.3680806159973145
                ],
                [
                    -0.3420201539993286,
                    4.10752676316406e-08,
                    0.9396926164627075,
                    3.75877046585083
                ],
                [
                    0.0,
                    1.0,
                    -4.371138828673793e-08,
                    0.0
                ],
                [
                    0.0,
                    0.0,
                    0.0,
                    1.0
                ]
            ]
        },
        {
            "file_path": "train/0057",
            "transform_matrix": [
                [
                    -0.9161083698272705,
                    -1.752524170228753e-08,
                    -0.400930792093277,
                    -1.603723168373108
                ],
                [
                    -0.400930792093277,
                    4.00443695980357e-08,
                    0.9161083698272705,
                    3.664433479309082
                ],
                [
                    0.0,
                    1.0,
                    -4.371138828673793e-08,
                    0.0
                ],
                [
                    0.0,
                    0.0,
                    0.0,
                    1.0
                ]
            ]
        },
        {
            "file_path": "train/0058",
            "transform_matrix": [
                [
                    -0.8888354301452637,
                    -2.0029720104730586e-08,
                    -0.45822659134864807,
                    -1.8329063653945923
                ],
                [
                    -0.45822659134864807,
                    3.885223165411844e-08,
                    0.8888354301452637,
                    3.5553417205810547
                ],
                [
                    0.0,
                    1.0,
                    -4.371138828673793e-08,
                    0.0
                ],
                [
                    0.0,
                    0.0,
                    0.0,
                    1.0
                ]
            ]
        },
        {
            "file_path": "train/0059",
            "transform_matrix": [
                [
                    -0.8579834699630737,
                    -2.245354835395119e-08,
                    -0.5136772990226746,
                    -2.0547091960906982
                ],
                [
                    -0.5136772990226746,
                    3.75036499633552e-08,
                    0.8579834699630737,
                    3.431933879852295
                ],
                [
                    0.0,
                    1.0,
                    -4.371138828673793e-08,
                    0.0
                ],
                [
                    0.0,
                    0.0,
                    0.0,
                    1.0
                ]
            ]
        },
        {
            "file_path": "train/0060",
            "transform_matrix": [
                [
                    -0.8236765265464783,
                    -2.4786979579971558e-08,
                    -0.5670599937438965,
                    -2.268239974975586
                ],
                [
                    -0.5670599937438965,
                    3.600404596681983e-08,
                    0.8236765265464783,
                    3.294706106185913
                ],
                [
                    0.0,
                    1.0,
                    -4.371138828673793e-08,
                    0.0
                ],
                [
                    0.0,
                    0.0,
                    0.0,
                    1.0
                ]
            ]
        },
        {
            "file_path": "train/0061",
            "transform_matrix": [
                [
                    -0.7860531210899353,
                    -2.7020584880688148e-08,
                    -0.6181589365005493,
                    -2.4726357460021973
                ],
                [
                    -0.6181589365005493,
                    3.4359473488621006e-08,
                    0.7860531210899353,
                    3.144212484359741
                ],
                [
                    0.0,
                    1.0,
                    -4.371138828673793e-08,
                    0.0
                ],
                [
                    0.0,
                    0.0,
                    0.0,
                    1.0
                ]
            ]
        },
        {
            "file_path": "train/0062",
            "transform_matrix": [
                [
                    -0.7452642917633057,
                    -2.9145404312203027e-08,
                    -0.6667691469192505,
                    -2.667076587677002
                ],
                [
                    -0.6667691469192505,
                    3.257653702348762e-08,
                    0.7452642917633057,
                    2.9810571670532227
                ],
                [
                    0.0,
                    1.0,
                    -4.371138828673793e-08,
                    0.0
                ],
                [
                    0.0,
                    0.0,
                    0.0,
                    1.0
                ]
            ]
        },
        {
            "file_path": "train/0063",
            "transform_matrix": [
                [
                    -0.7014749050140381,
                    -3.1152850965554535e-08,
                    -0.7126941680908203,
                    -2.8507766723632812
                ],
                [
                    -0.7126941680908203,
                    3.066244147476027e-08,
                    0.7014749050140381,
                    2.8058996200561523
                ],
                [
                    0.0,
                    1.0,
                    -4.371138828673793e-08,
                    0.0
                ],
                [
                    0.0,
                    0.0,
                    0.0,
                    1.0
                ]
            ]
        },
        {
            "file_path": "train/0064",
            "transform_matrix": [
                [
                    -0.6548605561256409,
                    -3.303487261518967e-08,
                    -0.7557497620582581,
                    -3.0229990482330322
                ],
                [
                    -0.7557497620582581,
                    2.8624864256698856e-08,
                    0.6548605561256409,
                    2.6194422245025635
                ],
                [
                    0.0,
                    1.0,
                    -4.371138828673793e-08,
                    0.0
                ],
                [
                    0.0,
                    0.0,
                    0.0,
                    1.0
                ]
            ]
        },
        {
            "file_path": "train/0065",
            "transform_matrix": [
                [
                    -0.605609655380249,
                    -3.478385579569476e-08,
                    -0.7957618832588196,
                    -3.1830475330352783
                ],
                [
                    -0.7957618832588196,
                    2.6472038783253993e-08,
                    0.605609655380249,
                    2.422438621520996
                ],
                [
                    0.0,
                    1.0,
                    -4.371138828673793e-08,
                    0.0
                ],
                [
                    0.0,
                    0.0,
                    0.0,
                    1.0
                ]
            ]
        },
        {
            "file_path": "train/0066",
            "transform_matrix": [
                [
                    -0.5539199709892273,
                    -3.639278745026786e-08,
                    -0.8325698971748352,
                    -3.330279588699341
                ],
                [
                    -0.8325698971748352,
                    2.421261058316304e-08,
                    0.5539199709892273,
                    2.215679883956909
                ],
                [
                    0.0,
                    1.0,
                    -4.371138828673793e-08,
                    0.0
                ],
                [
                    0.0,
                    0.0,
                    0.0,
                    1.0
                ]
            ]
        },
        {
            "file_path": "train/0067",
            "transform_matrix": [
                [
                    -0.49999991059303284,
                    -3.785517321830412e-08,
                    -0.866025447845459,
                    -3.464101791381836
                ],
                [
                    -0.866025447845459,
                    2.1855690590655286e-08,
                    0.49999991059303284,
                    1.9999996423721313
                ],
                [
                    0.0,
                    1.0,
                    -4.371138828673793e-08,
                    0.0
                ],
                [
                    0.0,
                    0.0,
                    0.0,
                    1.0
                ]
            ]
        },
        {
            "file_path": "train/0068",
            "transform_matrix": [
                [
                    -0.44406649470329285,
                    -3.9165133358665116e-08,
                    -0.8959938287734985,
                    -3.583975315093994
                ],
                [
                    -0.8959938287734985,
                    1.9410762774896284e-08,
                    0.44406649470329285,
                    1.7762659788131714
                ],
                [
                    0.0,
                    1.0,
                    -4.371138828673793e-08,
                    0.0
                ],
                [
                    0.0,
                    0.0,
                    0.0,
                    1.0
                ]
            ]
        },
        {
            "file_path": "train/0069",
            "transform_matrix": [
                [
                    -0.3863449692726135,
                    -4.031738853882416e-08,
                    -0.9223543405532837,
                    -3.6894173622131348
                ],
                [
                    -0.9223543405532837,
                    1.688767525820367e-08,
                    0.3863449692726135,
                    1.545379877090454
                ],
                [
                    0.0,
                    1.0,
                    -4.371138828673793e-08,
                    0.0
                ],
                [
                    0.0,
                    0.0,
                    0.0,
                    1.0
                ]
            ]
        },
        {
            "file_path": "train/0070",
            "transform_matrix": [
                [
                    -0.3270677626132965,
                    -4.130730246743042e-08,
                    -0.9450008869171143,
                    -3.780003547668457
                ],
                [
                    -0.9450008869171143,
                    1.4296586137163558e-08,
                    0.3270677626132965,
                    1.308271050453186
                ],
                [
                    0.0,
                    1.0,
                    -4.371138828673793e-08,
                    0.0
                ],
                [
                    0.0,
                    0.0,
                    0.0,
                    1.0
                ]
            ]
        },
        {
            "file_path": "train/0071",
            "transform_matrix": [
                [
                    -0.26647359132766724,
                    -4.2130881894308914e-08,
                    -0.9638422131538391,
                    -3.8553688526153564
                ],
                [
                    -0.9638422131538391,
                    1.1647930620029001e-08,
                    0.26647359132766724,
                    1.065894365310669
                ],
                [
                    0.0,
                    1.0,
                    -4.371138828673793e-08,
                    0.0
                ],
                [
                    0.0,
                    0.0,
                    0.0,
                    1.0
                ]
            ]
        },
        {
            "file_path": "train/0072",
            "transform_matrix": [
                [
                    -0.2048064023256302,
                    -4.2784815690311007e-08,
                    -0.978802502155304,
                    -3.915210008621216
                ],
                [
                    -0.978802502155304,
                    8.95237217690692e-09,
                    0.2048064023256302,
                    0.8192256093025208
                ],
                [
                    0.0,
                    1.0,
                    -4.371138828673793e-08,
                    0.0
                ],
                [
                    0.0,
                    0.0,
                    0.0,
                    1.0
                ]
            ]
        },
        {
            "file_path": "train/0073",
            "transform_matrix": [
                [
                    -0.14231501519680023,
                    -4.326646774188703e-08,
                    -0.9898214340209961,
                    -3.9592857360839844
                ],
                [
                    -0.9898214340209961,
                    6.220786996635752e-09,
                    0.14231501519680023,
                    0.5692600607872009
                ],
                [
                    0.0,
                    1.0,
                    -4.371138828673793e-08,
                    0.0
                ],
                [
                    0.0,
                    0.0,
                    0.0,
                    1.0
                ]
            ]
        },
        {
            "file_path": "train/0074",
            "transform_matrix": [
                [
                    -0.07924962788820267,
                    -4.357390537279571e-08,
                    -0.9968547821044922,
                    -3.9874191284179688
                ],
                [
                    -0.9968547821044922,
                    3.4641112200972657e-09,
                    0.07924962788820267,
                    0.31699851155281067
                ],
                [
                    0.0,
                    1.0,
                    -4.371138828673793e-08,
                    0.0
                ],
                [
                    0.0,
                    0.0,
                    0.0,
                    1.0
                ]
            ]
        },
        {
            "file_path": "train/0075",
            "transform_matrix": [
                [
                    -0.015866078436374664,
                    -4.370588513324947e-08,
                    -0.9998741149902344,
                    -3.9994964599609375
                ],
                [
                    -0.9998741149902344,
                    6.935282903519635e-10,
                    0.015866078436374664,
                    0.06346431374549866
                ],
                [
                    0.0,
                    1.0,
                    -4.371138828673793e-08,
                    0.0
                ],
                [
                    0.0,
                    0.0,
                    0.0,
                    1.0
                ]
            ]
        },
        {
            "file_path": "train/0076",
            "transform_matrix": [
                [
                    0.04758230969309807,
                    -4.3661877668910165e-08,
                    -0.9988673329353333,
                    -3.995469331741333
                ],
                [
                    -0.9988673329353333,
                    -2.0798887057082993e-09,
                    -0.04758230969309807,
                    -0.19032923877239227
                ],
                [
                    0.0,
                    1.0,
                    -4.371138828673793e-08,
                    0.0
                ],
                [
                    0.0,
                    0.0,
                    0.0,
                    1.0
                ]
            ]
        },
        {
            "file_path": "train/0077",
            "transform_matrix": [
                [
                    0.1108381450176239,
                    -4.344206061546174e-08,
                    -0.9938384890556335,
                    -3.975353956222534
                ],
                [
                    -0.9938384890556335,
                    -4.844889378574635e-09,
                    -0.1108381450176239,
                    -0.4433525800704956
                ],
                [
                    0.0,
                    1.0,
                    -4.371138828673793e-08,
                    0.0
                ],
                [
                    0.0,
                    0.0,
                    0.0,
                    1.0
                ]
            ]
        },
        {
            "file_path": "train/0078",
            "transform_matrix": [
                [
                    0.1736481487751007,
                    -4.304731149318286e-08,
                    -0.9848077297210693,
                    -3.9392309188842773
                ],
                [
                    -0.9848077297210693,
                    -7.59040208464512e-09,
                    -0.1736481487751007,
                    -0.6945925951004028
                ],
                [
                    0.0,
                    1.0,
                    -4.371138828673793e-08,
                    0.0
                ],
                [
                    0.0,
                    0.0,
                    0.0,
                    1.0
                ]
            ]
        },
        {
            "file_path": "train/0079",
            "transform_matrix": [
                [
                    0.2357589453458786,
                    -4.247923257594266e-08,
                    -0.9718115925788879,
                    -3.8872463703155518
                ],
                [
                    -0.9718115925788879,
                    -1.0305351239026095e-08,
                    -0.2357589453458786,
                    -0.9430357813835144
                ],
                [
                    0.0,
                    1.0,
                    -4.371138828673793e-08,
                    0.0
                ],
                [
                    0.0,
                    0.0,
                    0.0,
                    1.0
                ]
            ]
        },
        {
            "file_path": "train/0080",
            "transform_matrix": [
                [
                    0.29692041873931885,
                    -4.174010115320925e-08,
                    -0.9549022316932678,
                    -3.8196089267730713
                ],
                [
                    -0.9549022316932678,
                    -1.297880380946026e-08,
                    -0.29692041873931885,
                    -1.1876816749572754
                ],
                [
                    0.0,
                    1.0,
                    -4.371138828673793e-08,
                    0.0
                ],
                [
                    0.0,
                    0.0,
                    0.0,
                    1.0
                ]
            ]
        },
        {
            "file_path": "train/0081",
            "transform_matrix": [
                [
                    0.3568862974643707,
                    -4.083289795175915e-08,
                    -0.934147834777832,
                    -3.736591339111328
                ],
                [
                    -0.934147834777832,
                    -1.559999596167927e-08,
                    -0.3568862974643707,
                    -1.427545189857483
                ],
                [
                    0.0,
                    1.0,
                    -4.371138828673793e-08,
                    0.0
                ],
                [
                    0.0,
                    0.0,
                    0.0,
                    1.0
                ]
            ]
        },
        {
            "file_path": "train/0082",
            "transform_matrix": [
                [
                    0.41541510820388794,
                    -3.976127516125416e-08,
                    -0.9096319675445557,
                    -3.6385278701782227
                ],
                [
                    -0.9096319675445557,
                    -1.8158370806986568e-08,
                    -0.41541510820388794,
                    -1.6616604328155518
                ],
                [
                    0.0,
                    1.0,
                    -4.371138828673793e-08,
                    0.0
                ],
                [
                    0.0,
                    0.0,
                    0.0,
                    1.0
                ]
            ]
        },
        {
            "file_path": "train/0083",
            "transform_matrix": [
                [
                    0.472271203994751,
                    -3.852954577610035e-08,
                    -0.881453275680542,
                    -3.525813102722168
                ],
                [
                    -0.881453275680542,
                    -2.0643630804784152e-08,
                    -0.472271203994751,
                    -1.889084815979004
                ],
                [
                    0.0,
                    1.0,
                    -4.371138828673793e-08,
                    0.0
                ],
                [
                    0.0,
                    0.0,
                    0.0,
                    1.0
                ]
            ]
        },
        {
            "file_path": "train/0084",
            "transform_matrix": [
                [
                    0.5272256135940552,
                    -3.7142676490020676e-08,
                    -0.8497253656387329,
                    -3.3989014625549316
                ],
                [
                    -0.8497253656387329,
                    -2.3045762631568323e-08,
                    -0.5272256135940552,
                    -2.1089024543762207
                ],
                [
                    0.0,
                    1.0,
                    -4.371138828673793e-08,
                    0.0
                ],
                [
                    0.0,
                    0.0,
                    0.0,
                    1.0
                ]
            ]
        },
        {
            "file_path": "train/0085",
            "transform_matrix": [
                [
                    0.5800570845603943,
                    -3.560624151077718e-08,
                    -0.8145758509635925,
                    -3.25830340385437
                ],
                [
                    -0.8145758509635925,
                    -2.5355101129775903e-08,
                    -0.5800570845603943,
                    -2.320228338241577
                ],
                [
                    0.0,
                    1.0,
                    -4.371138828673793e-08,
                    0.0
                ],
                [
                    0.0,
                    0.0,
                    0.0,
                    1.0
                ]
            ]
        },
        {
            "file_path": "train/0086",
            "transform_matrix": [
                [
                    0.6305524706840515,
                    -3.392644742916673e-08,
                    -0.776146650314331,
                    -3.104586601257324
                ],
                [
                    -0.776146650314331,
                    -2.756232397871372e-08,
                    -0.6305524706840515,
                    -2.522209882736206
                ],
                [
                    0.0,
                    1.0,
                    -4.371138828673793e-08,
                    0.0
                ],
                [
                    0.0,
                    0.0,
                    0.0,
                    1.0
                ]
            ]
        },
        {
            "file_path": "train/0087",
            "transform_matrix": [
                [
                    0.6785095930099487,
                    -3.211001597946961e-08,
                    -0.734591543674469,
                    -2.938366174697876
                ],
                [
                    -0.734591543674469,
                    -2.96585955794626e-08,
                    -0.6785095930099487,
                    -2.714038372039795
                ],
                [
                    0.0,
                    1.0,
                    -4.371138828673793e-08,
                    0.0
                ],
                [
                    0.0,
                    0.0,
                    0.0,
                    1.0
                ]
            ]
        },
        {
            "file_path": "train/0088",
            "transform_matrix": [
                [
                    0.7237342596054077,
                    -3.016430127900094e-08,
                    -0.6900787949562073,
                    -2.760315179824829
                ],
                [
                    -0.6900787949562073,
                    -3.163543027540072e-08,
                    -0.7237342596054077,
                    -2.894937038421631
                ],
                [
                    0.0,
                    1.0,
                    -4.371138828673793e-08,
                    0.0
                ],
                [
                    0.0,
                    0.0,
                    0.0,
                    1.0
                ]
            ]
        },
        {
            "file_path": "train/0089",
            "transform_matrix": [
                [
                    0.7660446166992188,
                    -2.8097129955995115e-08,
                    -0.6427873969078064,
                    -2.5711495876312256
                ],
                [
                    -0.6427873969078064,
                    -3.3484873540601257e-08,
                    -0.7660446166992188,
                    -3.064178466796875
                ],
                [
                    0.0,
                    1.0,
                    -4.371138828673793e-08,
                    0.0
                ],
                [
                    0.0,
                    0.0,
                    0.0,
                    1.0
                ]
            ]
        },
        {
            "file_path": "train/0090",
            "transform_matrix": [
                [
                    0.8052701950073242,
                    -2.5916833124028926e-08,
                    -0.5929080247879028,
                    -2.3716320991516113
                ],
                [
                    -0.5929080247879028,
                    -3.51994771108366e-08,
                    -0.8052701950073242,
                    -3.221080780029297
                ],
                [
                    0.0,
                    1.0,
                    -4.371138828673793e-08,
                    0.0
                ],
                [
                    0.0,
                    0.0,
                    0.0,
                    1.0
                ]
            ]
        },
        {
            "file_path": "train/0091",
            "transform_matrix": [
                [
                    0.8412537574768066,
                    -2.3632145129681703e-08,
                    -0.5406404733657837,
                    -2.1625618934631348
                ],
                [
                    -0.5406404733657837,
                    -3.677237003785194e-08,
                    -0.8412537574768066,
                    -3.3650150299072266
                ],
                [
                    0.0,
                    1.0,
                    -4.371138828673793e-08,
                    0.0
                ],
                [
                    0.0,
                    0.0,
                    0.0,
                    1.0
                ]
            ]
        },
        {
            "file_path": "train/0092",
            "transform_matrix": [
                [
                    0.8738495707511902,
                    -2.125231901572988e-08,
                    -0.486196368932724,
                    -1.944785475730896
                ],
                [
                    -0.486196368932724,
                    -3.8197178753307526e-08,
                    -0.8738495707511902,
                    -3.4953982830047607
                ],
                [
                    0.0,
                    1.0,
                    -4.371138828673793e-08,
                    0.0
                ],
                [
                    0.0,
                    0.0,
                    0.0,
                    1.0
                ]
            ]
        },
        {
            "file_path": "train/0093",
            "transform_matrix": [
                [
                    0.902926504611969,
                    -1.8786932898251507e-08,
                    -0.42979493737220764,
                    -1.7191797494888306
                ],
                [
                    -0.42979493737220764,
                    -3.946817273003944e-08,
                    -0.902926504611969,
                    -3.611706018447876
                ],
                [
                    0.0,
                    1.0,
                    -4.371138828673793e-08,
                    0.0
                ],
                [
                    0.0,
                    0.0,
                    0.0,
                    1.0
                ]
            ]
        },
        {
            "file_path": "train/0094",
            "transform_matrix": [
                [
                    0.9283679127693176,
                    -1.624588286119888e-08,
                    -0.3716624677181244,
                    -1.4866498708724976
                ],
                [
                    -0.3716624677181244,
                    -4.058025027120493e-08,
                    -0.9283679127693176,
                    -3.7134716510772705
                ],
                [
                    0.0,
                    1.0,
                    -4.371138828673793e-08,
                    0.0
                ],
                [
                    0.0,
                    0.0,
                    0.0,
                    1.0
                ]
            ]
        },
        {
            "file_path": "train/0095",
            "transform_matrix": [
                [
                    0.9500712752342224,
                    -1.3639394502718005e-08,
                    -0.3120329678058624,
                    -1.2481318712234497
                ],
                [
                    -0.3120329678058624,
                    -4.152893495756871e-08,
                    -0.9500712752342224,
                    -3.8002851009368896
                ],
                [
                    0.0,
                    1.0,
                    -4.371138828673793e-08,
                    0.0
                ],
                [
                    0.0,
                    0.0,
                    0.0,
                    1.0
                ]
            ]
        },
        {
            "file_path": "train/0096",
            "transform_matrix": [
                [
                    0.967948853969574,
                    -1.0978005171580207e-08,
                    -0.25114747881889343,
                    -1.0045899152755737
                ],
                [
                    -0.25114747881889343,
                    -4.2310389858357667e-08,
                    -0.967948853969574,
                    -3.871795415878296
                ],
                [
                    0.0,
                    1.0,
                    -4.371138828673793e-08,
                    0.0
                ],
                [
                    0.0,
                    0.0,
                    0.0,
                    1.0
                ]
            ]
        },
        {
            "file_path": "train/0097",
            "transform_matrix": [
                [
                    0.9819287061691284,
                    -8.272431628597587e-09,
                    -0.18925116956233978,
                    -0.7570046782493591
                ],
                [
                    -0.18925116956233978,
                    -4.292146726925239e-08,
                    -0.9819287061691284,
                    -3.9277148246765137
                ],
                [
                    0.0,
                    1.0,
                    -4.371138828673793e-08,
                    0.0
                ],
                [
                    0.0,
                    0.0,
                    0.0,
                    1.0
                ]
            ]
        },
        {
            "file_path": "train/0098",
            "transform_matrix": [
                [
                    0.9919548034667969,
                    -5.533526969969671e-09,
                    -0.12659233808517456,
                    -0.5063693523406982
                ],
                [
                    -0.12659233808517456,
                    -4.335972292324186e-08,
                    -0.9919548034667969,
                    -3.9678192138671875
                ],
                [
                    0.0,
                    1.0,
                    -4.371138828673793e-08,
                    0.0
                ],
                [
                    0.0,
                    0.0,
                    0.0,
                    1.0
                ]
            ]
        },
        {
            "file_path": "train/0099",
            "transform_matrix": [
                [
                    0.9979866743087769,
                    -2.7723412454605523e-09,
                    -0.0634237751364708,
                    -0.2536951005458832
                ],
                [
                    -0.0634237751364708,
                    -4.362338401620036e-08,
                    -0.9979866743087769,
                    -3.9919466972351074
                ],
                [
                    0.0,
                    1.0,
                    -4.371138828673793e-08,
                    0.0
                ],
                [
                    0.0,
                    0.0,
                    0.0,
                    1.0
                ]
            ]
        },
        {
            "file_path": "train/0100",
            "transform_matrix": [
                [
                    1.0,
                    7.64274186065882e-15,
                    1.7484555314695172e-07,
                    6.993822125878069e-07
                ],
                [
                    1.7484555314695172e-07,
                    -4.371138828673793e-08,
                    -1.0,
                    -4.0
                ],
                [
                    0.0,
                    1.0,
                    -4.371138828673793e-08,
                    0.0
                ],
                [
                    0.0,
                    0.0,
                    0.0,
                    1.0
                ]
            ]
        }
    ]
}